AUTHORS.txt
CHANGES.rst
CLASSIFIERS.txt
LICENSE
MANIFEST.in
README.rst
REQUIREMENTS.txt
setup.py
flask_bluelogin/__init__.py
flask_bluelogin/__init__.pyc
flask_bluelogin/main.py
flask_bluelogin/main.pyc
flask_bluelogin/util.py
flask_bluelogin/util.pyc
flask_bluelogin.egg-info/PKG-INFO
flask_bluelogin.egg-info/SOURCES.txt
flask_bluelogin.egg-info/dependency_links.txt
flask_bluelogin.egg-info/requires.txt
flask_bluelogin.egg-info/top_level.txt
flask_bluelogin/__pycache__/__init__.cpython-36.pyc
flask_bluelogin/__pycache__/main.cpython-36.pyc
flask_bluelogin/__pycache__/util.cpython-36.pyc
flask_bluelogin/controllers/__init__.py
flask_bluelogin/controllers/__init__.pyc
flask_bluelogin/controllers/login_controller.py
flask_bluelogin/controllers/login_controller.pyc
flask_bluelogin/controllers/__pycache__/__init__.cpython-36.pyc
flask_bluelogin/controllers/__pycache__/login_controller.cpython-36.pyc
flask_bluelogin/models/__init__.py
flask_bluelogin/models/__init__.pyc
flask_bluelogin/models/base_model_.py
flask_bluelogin/models/base_model_.pyc
flask_bluelogin/models/error_model.py
flask_bluelogin/models/error_model.pyc
flask_bluelogin/models/user.py
flask_bluelogin/models/user.pyc
flask_bluelogin/models/users.py
flask_bluelogin/models/users.pyc
flask_bluelogin/models/__pycache__/__init__.cpython-36.pyc
flask_bluelogin/models/__pycache__/base_model_.cpython-36.pyc
flask_bluelogin/models/__pycache__/error_model.cpython-36.pyc
flask_bluelogin/models/__pycache__/user.cpython-36.pyc
flask_bluelogin/models/__pycache__/users.cpython-36.pyc
flask_bluelogin/swagger-ui/index.html
flask_bluelogin/swagger-ui/o2c.html
flask_bluelogin/swagger-ui/swagger-ui.js
flask_bluelogin/swagger-ui/swagger-ui.min.js
flask_bluelogin/swagger-ui/swagger.yaml
flask_bluelogin/swagger-ui/css/print.css
flask_bluelogin/swagger-ui/css/reset.css
flask_bluelogin/swagger-ui/css/screen.css
flask_bluelogin/swagger-ui/css/style.css
flask_bluelogin/swagger-ui/css/typography.css
flask_bluelogin/swagger-ui/fonts/DroidSans-Bold.ttf
flask_bluelogin/swagger-ui/fonts/DroidSans.ttf
flask_bluelogin/swagger-ui/images/collapse.gif
flask_bluelogin/swagger-ui/images/expand.gif
